__init__.py
explore/__init__.py
explore/app.py
explore/constants.py
explore/io.py
explore/main.py
explore/sidebar.py
explore/utils.py
explore/containers/cockpit_container/data_artifact_selection.py
explore/containers/cockpit_container/graph_container.py
explore/containers/cockpit_container/main.py
explore/containers/cockpit_container/utils.py
explore/containers/columns_stats_container/main.py
explore/containers/correlations/constants.py
explore/containers/correlations/corr_user_input.py
explore/containers/correlations/correlation_matrix.py
explore/containers/correlations/correlation_table.py
explore/containers/correlations/main.py
explore/containers/correlations/mutual_info.py
explore/containers/correlations/pearson_corr.py
explore/containers/correlations/st_explanations.py
explore/containers/correlations/umap.py
explore/containers/data_exploration/constants.py
explore/containers/data_exploration/main.py
explore/containers/data_exploration/plot.py
explore/containers/experiments/main.py
explore/containers/metrics/main.py
explore/containers/model/constants.py
explore/containers/model/main.py
explore/containers/params/main.py
explore/containers/sample_df/main.py
explore/resources/horizontal-color.svg
visium_explore-0.67.0.dist-info/METADATA
visium_explore-0.67.0.dist-info/WHEEL
visium_explore-0.67.0.dist-info/entry_points.txt
visium_explore-0.67.0.dist-info/top_level.txt
visium_explore-0.67.0.dist-info/RECORD
