Metadata-Version: 2.4
Name: visium-explore
Version: 0.67.0
Summary: Explore is a Python library to explore the artifacts of your DVC pipeline.
Author-email: Adrien Ruault <ar@visium.ch>
Requires-Python: >=3.7
Requires-Dist: streamlit>=1.35.0
Requires-Dist: plotly
Requires-Dist: pydantic
Requires-Dist: pyyaml
Requires-Dist: dvc
Requires-Dist: mlflow
Requires-Dist: pandera>=0.18.3
Requires-Dist: phik
Requires-Dist: umap-learn
Requires-Dist: watchdog
Requires-Dist: protobuf>=3.13.0
